mrscrub/__init__.py
mrscrub/__version__.py
mrscrub/configs/PBN_v1.0.yaml
mrscrub/configs/PBN_v2.0.yaml
mrscrub/configs/__init__.py
mrscrub/dicom/__init__.py
mrscrub/scanner/__init__.py
mrscrub-0.4.2.data/scripts/scrub.py
mrscrub-0.4.2.dist-info/licenses/LICENSE
mrscrub-0.4.2.dist-info/METADATA
mrscrub-0.4.2.dist-info/WHEEL
mrscrub-0.4.2.dist-info/top_level.txt
mrscrub-0.4.2.dist-info/RECORD
