Metadata-Version: 2.4
Name: mrscrub
Version: 0.4.2
Summary: MR data deidentifer
Home-page: https://github.com/harvard-nrg/mrscrub
Author: Neuroinformatics Research Group
Author-email: info@neuroinfo.org
License-File: LICENSE
Requires-Dist: pydicom
Requires-Dist: pyyaml
Requires-Dist: tqdm
Dynamic: author
Dynamic: author-email
Dynamic: home-page
Dynamic: license-file
Dynamic: requires-dist
Dynamic: summary
